rfproto/__init__.py
rfproto/agc_magest.py
rfproto/filter.py
rfproto/frequency.py
rfproto/fxp_int.py
rfproto/impairments.py
rfproto/measurements.py
rfproto/modulation.py
rfproto/multirate.py
rfproto/nco.py
rfproto/pi_filter.py
rfproto/plot.py
rfproto/sig_gen.py
rfproto/signal.py
rfproto/utils.py
rfproto-0.0.17.dist-info/licenses/LICENSE
rfproto-0.0.17.dist-info/METADATA
rfproto-0.0.17.dist-info/WHEEL
rfproto-0.0.17.dist-info/top_level.txt
rfproto-0.0.17.dist-info/RECORD
