Metadata-Version: 2.4
Name: rfproto
Version: 0.0.17
Summary: Python for RF and SDR prototyping.
Author-email: John Gentile <johncgentile17@gmail.com>
Project-URL: Homepage, https://github.com/JohnnyGOX17/rfproto
Project-URL: Documentation, https://johnnygox17.github.io/rfproto/
Project-URL: Issues, https://github.com/JohnnyGOX17/rfproto/issues
Project-URL: Repository, https://github.com/JohnnyGOX17/rfproto.git
Keywords: RF,SDR,prototyping
Classifier: Programming Language :: Python :: 3
Classifier: License :: OSI Approved :: MIT License
Classifier: Operating System :: OS Independent
Requires-Python: >=3.8
License-File: LICENSE
Requires-Dist: control
Requires-Dist: matplotlib
Requires-Dist: numpy
Requires-Dist: scipy
Provides-Extra: docs
Requires-Dist: mkdocs; extra == "docs"
Requires-Dist: mkdocstrings[python]; extra == "docs"
Requires-Dist: mkdocs-material; extra == "docs"
Provides-Extra: test
Requires-Dist: black; extra == "test"
Requires-Dist: mypy; extra == "test"
Requires-Dist: pytest; extra == "test"
Requires-Dist: pytest-cov; extra == "test"
Dynamic: license-file
